AUTHORS
CHANGES.rst
LICENSE
MANIFEST.in
README.rst
setup.py
django_less.egg-info/PKG-INFO
django_less.egg-info/SOURCES.txt
django_less.egg-info/dependency_links.txt
django_less.egg-info/top_level.txt
less/__init__.py
less/cache.py
less/devmode.py
less/finders.py
less/models.py
less/settings.py
less/storage.py
less/utils.py
less/templatetags/__init__.py
less/templatetags/less.py
less/tests/__init__.py
less/tests/django_settings.py
less/tests/tests.py