Metadata-Version: 1.0
Name: django-less
Version: 0.7.2
Summary: Django template tags to compile LESS into CSS
Home-page: https://github.com/andreyfedoseev/django-less
Author: Andrey Fedoseev
Author-email: andrey.fedoseev@gmail.com
License: UNKNOWN
Keywords: less,css
Platform: UNKNOWN
Classifier: Development Status :: 4 - Beta
Classifier: Framework :: Django
Classifier: Intended Audience :: Developers
Classifier: License :: OSI Approved :: BSD License
Classifier: Operating System :: OS Independent
Classifier: Programming Language :: Python
Classifier: Topic :: Internet :: WWW/HTTP
